paradime/__init__.py
paradime/apis/__init__.py
paradime/apis/audit_log/__init__.py
paradime/apis/audit_log/client.py
paradime/apis/audit_log/types.py
paradime/apis/bolt/__init__.py
paradime/apis/bolt/client.py
paradime/apis/bolt/exception.py
paradime/apis/bolt/types.py
paradime/apis/catalog/__init__.py
paradime/apis/catalog/client.py
paradime/apis/custom_integration/__init__.py
paradime/apis/custom_integration/client.py
paradime/apis/custom_integration/types.py
paradime/apis/custom_integration/utils.py
paradime/apis/lineage_diff/__init__.py
paradime/apis/lineage_diff/client.py
paradime/apis/lineage_diff/exception.py
paradime/apis/lineage_diff/types.py
paradime/apis/users/__init__.py
paradime/apis/users/client.py
paradime/apis/users/types.py
paradime/apis/workspaces/__init__.py
paradime/apis/workspaces/client.py
paradime/apis/workspaces/types.py
paradime/cli/__init__.py
paradime/cli/bolt.py
paradime/cli/catalog.py
paradime/cli/cli.py
paradime/cli/login.py
paradime/cli/rich_text_output.py
paradime/cli/run.py
paradime/cli/utils.py
paradime/cli/version.py
paradime/client/api_client.py
paradime/client/api_exception.py
paradime/client/paradime_cli_client.py
paradime/client/paradime_client.py
paradime/core/__init__.py
paradime/core/bolt/__init__.py
paradime/core/bolt/schedule.py
paradime/core/bolt/timezones.py
paradime/core/scripts/__init__.py
paradime/core/scripts/airbyte.py
paradime/core/scripts/fivetran.py
paradime/core/scripts/montecarlo.py
paradime/core/scripts/power_bi.py
paradime/core/scripts/tableau.py
paradime/core/scripts/utils.py
paradime/tools/__init__.py
paradime/tools/pydantic.py
paradime/version.py
paradime_io-4.18.0.dist-info/LICENSE
paradime_io-4.18.0.dist-info/METADATA
paradime_io-4.18.0.dist-info/WHEEL
paradime_io-4.18.0.dist-info/entry_points.txt
paradime_io-4.18.0.dist-info/RECORD
