Metadata-Version: 2.1
Name: paradime-io
Version: 4.18.0
Summary: Paradime - Python SDK
Author: Bhuvan Singla
Author-email: bhuvan@paradime.io
Requires-Python: >=3.8.1
Classifier: Programming Language :: Python :: 3
Classifier: Programming Language :: Python :: 3.9
Classifier: Programming Language :: Python :: 3.10
Classifier: Programming Language :: Python :: 3.11
Classifier: Programming Language :: Python :: 3.12
Classifier: Programming Language :: Python :: 3.13
Requires-Dist: click (>=8.1.7,<9.0.0)
Requires-Dist: croniter (>=6.0.0,<7.0.0)
Requires-Dist: msal (>=1.31.0,<2.0.0)
Requires-Dist: packaging (>21.0)
Requires-Dist: pydantic (>=1.10.14,<3.0.0)
Requires-Dist: python-dotenv (>=1.0.1,<2.0.0)
Requires-Dist: pyyaml (>=6.0.1,<7.0.0)
Requires-Dist: requests (>=2.31.0,<3.0.0)
Requires-Dist: rich (>=14.0.0,<15.0.0)
